libname/__init__.py
libname/hello.py
demotestkdw-0.0.13.dist-info/METADATA
demotestkdw-0.0.13.dist-info/WHEEL
demotestkdw-0.0.13.dist-info/top_level.txt
demotestkdw-0.0.13.dist-info/RECORD
