Metadata-Version: 2.1
Name: demotestkdw
Version: 0.0.13
Summary: Demo file
Author: kdwivedi
Author-email: <kdwivedi@materialise.be>
License: UNKNOWN
Keywords: python
Platform: UNKNOWN
Classifier: Development Status :: 1 - Planning
Classifier: Intended Audience :: Developers
Classifier: Programming Language :: Python :: 3
Classifier: Operating System :: Microsoft :: Windows
